[{"collegeName":"Indian Institute of Technology Madras"},{"collegeName":"Indian Institute of Technology Delhi"},{"collegeName":"Indian Institute of Technology Bombay"},{"collegeName":"Institute of Technology Kanpur"},{"collegeName":"Indian Institute of Technology Kharagpur"},{"collegeName":"Indian Institute of Technology Roorkee"},{"collegeName":"Indian Institute of Technology Guwahati"},{"collegeName":"Institute of Technology Hyderabad"},{"collegeName":"National Institute of Technology Tiruchirappalli"}

,
{
    "collegeName":"National Institute of Technology Durgapur" 
},

{
    "collegeName":"National Institute of Technology Hamirpur" 
}
,{
    "collegeName":"National Institute of Technology Jamshedpur" 

},
{
    "collegeName":"National Institute of Technology Trichy" 

},
{
    "collegeName":"National Institute of Technology Warangal" 

}
]